README
setup.py
feincms_grid/__init__.py
feincms_grid/models.py
feincms_grid/settings.py
feincms_grid.egg-info/PKG-INFO
feincms_grid.egg-info/SOURCES.txt
feincms_grid.egg-info/dependency_links.txt
feincms_grid.egg-info/not-zip-safe
feincms_grid.egg-info/requires.txt
feincms_grid.egg-info/top_level.txt
feincms_grid/templatetags/__init__.py
feincms_grid/templatetags/feincms_grid_admin_tags.py
feincms_grid/templatetags/feincms_grid_tags.py