Metadata-Version: 1.1
Name: feincms-grid
Version: 0.1.2
Summary: Integrate CSS grids with FeinCMS contenttypes
Home-page: http://github.com/joshuajonah/feincms_grid
Author: Joshua Jonah
Author-email: joshuajonahcom@gmail.com
License: BSD
Keywords: django feincms foundation grid
Platform: UNKNOWN
Classifier: Development Status :: 3 - Alpha
Classifier: Intended Audience :: Developers
Classifier: License :: OSI Approved :: BSD License
Classifier: Topic :: Software Development
Classifier: Programming Language :: Python :: 2
Classifier: Programming Language :: Python :: 2.7
